flowforge/__init__.py
flowforge/agent.py
flowforge/agent_def.py
flowforge/client.py
flowforge/config.py
flowforge/context.py
flowforge/decorators.py
flowforge/exceptions.py
flowforge/execution.py
flowforge/network.py
flowforge/router.py
flowforge/steps.py
flowforge/tools.py
flowforge/triggers.py
flowforge/worker.py
flowforge/ai/__init__.py
flowforge/ai/providers.py
flowforge/dev/__init__.py
flowforge/dev/server.py
flowforge/integrations/__init__.py
flowforge/integrations/fastapi.py
flowforge_sdk-0.1.4.dist-info/METADATA
flowforge_sdk-0.1.4.dist-info/WHEEL
flowforge_sdk-0.1.4.dist-info/RECORD
