Metadata-Version: 2.4
Name: flowforge-sdk
Version: 0.1.4
Summary: Python SDK for FlowForge - AI workflow orchestration
Project-URL: Homepage, https://github.com/flowforge/flowforge
Project-URL: Documentation, https://flowforge.dev/docs
Project-URL: Repository, https://github.com/flowforge/flowforge
Author: FlowForge Team
License: MIT
Keywords: ai,async,durable,llm,orchestration,sdk,workflow
Classifier: Development Status :: 3 - Alpha
Classifier: Framework :: FastAPI
Classifier: Framework :: Flask
Classifier: Intended Audience :: Developers
Classifier: License :: OSI Approved :: MIT License
Classifier: Programming Language :: Python :: 3
Classifier: Programming Language :: Python :: 3.11
Classifier: Programming Language :: Python :: 3.12
Classifier: Topic :: Software Development :: Libraries :: Python Modules
Requires-Python: >=3.11
Requires-Dist: httpx>=0.25.0
Requires-Dist: pydantic>=2.0.0
Requires-Dist: typing-extensions>=4.8.0
Provides-Extra: ai
Requires-Dist: anthropic>=0.7.0; extra == 'ai'
Requires-Dist: litellm>=1.0.0; extra == 'ai'
Requires-Dist: openai>=1.0.0; extra == 'ai'
Provides-Extra: all
Requires-Dist: anthropic>=0.7.0; extra == 'all'
Requires-Dist: fastapi>=0.104.0; extra == 'all'
Requires-Dist: flask>=3.0.0; extra == 'all'
Requires-Dist: litellm>=1.0.0; extra == 'all'
Requires-Dist: mypy>=1.6.0; extra == 'all'
Requires-Dist: openai>=1.0.0; extra == 'all'
Requires-Dist: pytest-asyncio>=0.21.0; extra == 'all'
Requires-Dist: pytest-cov>=4.1.0; extra == 'all'
Requires-Dist: pytest>=7.4.0; extra == 'all'
Requires-Dist: ruff>=0.1.0; extra == 'all'
Requires-Dist: uvicorn>=0.24.0; extra == 'all'
Provides-Extra: dev
Requires-Dist: mypy>=1.6.0; extra == 'dev'
Requires-Dist: pytest-asyncio>=0.21.0; extra == 'dev'
Requires-Dist: pytest-cov>=4.1.0; extra == 'dev'
Requires-Dist: pytest>=7.4.0; extra == 'dev'
Requires-Dist: ruff>=0.1.0; extra == 'dev'
Provides-Extra: fastapi
Requires-Dist: fastapi>=0.104.0; extra == 'fastapi'
Requires-Dist: uvicorn>=0.24.0; extra == 'fastapi'
Provides-Extra: flask
Requires-Dist: flask>=3.0.0; extra == 'flask'
